html_toc/__init__.py
html_toc/test.py
html_toc-0.1.2.dist-info/WHEEL
html_toc-0.1.2.dist-info/METADATA
html_toc-0.1.2.dist-info/RECORD
